openstack_placement-14.0.0.data/scripts/placement-api
placement/__init__.py
placement/attribute_cache.py
placement/auth.py
placement/context.py
placement/db_api.py
placement/deploy.py
placement/direct.py
placement/errors.py
placement/exception.py
placement/fault_wrap.py
placement/handler.py
placement/lib.py
placement/microversion.py
placement/policy.py
placement/requestlog.py
placement/rest_api_version_history.rst
placement/util.py
placement/wsgi_wrapper.py
placement/cmd/__init__.py
placement/cmd/manage.py
placement/cmd/status.py
placement/conf/__init__.py
placement/conf/api.py
placement/conf/base.py
placement/conf/database.py
placement/conf/opts.py
placement/conf/paths.py
placement/conf/placement.py
placement/db/__init__.py
placement/db/constants.py
placement/db/sqlalchemy/__init__.py
placement/db/sqlalchemy/alembic.ini
placement/db/sqlalchemy/migration.py
placement/db/sqlalchemy/models.py
placement/db/sqlalchemy/alembic/env.py
placement/db/sqlalchemy/alembic/script.py.mako
placement/db/sqlalchemy/alembic/versions/422ece571366_add_consumer_types_table.py
placement/db/sqlalchemy/alembic/versions/611cd6dffd7b_block_on_null_root_provider_id.py
placement/db/sqlalchemy/alembic/versions/a082b8bb98d0_drop_redundant_indexes_for_unique_.py
placement/db/sqlalchemy/alembic/versions/b4ed3a175331_initial.py
placement/db/sqlalchemy/alembic/versions/b5c396305c25_block_on_null_consumer.py
placement/handlers/__init__.py
placement/handlers/aggregate.py
placement/handlers/allocation.py
placement/handlers/allocation_candidate.py
placement/handlers/inventory.py
placement/handlers/reshaper.py
placement/handlers/resource_class.py
placement/handlers/resource_provider.py
placement/handlers/root.py
placement/handlers/trait.py
placement/handlers/usage.py
placement/handlers/util.py
placement/objects/__init__.py
placement/objects/allocation.py
placement/objects/allocation_candidate.py
placement/objects/consumer.py
placement/objects/consumer_type.py
placement/objects/inventory.py
openstack_placement-14.0.0.dist-info/AUTHORS
openstack_placement-14.0.0.dist-info/LICENSE
openstack_placement-14.0.0.dist-info/METADATA
openstack_placement-14.0.0.dist-info/WHEEL
openstack_placement-14.0.0.dist-info/entry_points.txt
openstack_placement-14.0.0.dist-info/pbr.json
openstack_placement-14.0.0.dist-info/top_level.txt
openstack_placement-14.0.0.dist-info/RECORD
