Metadata-Version: 2.1
Name: openstack-placement
Version: 14.0.0
Summary: Resource provider inventory usage and allocation service
Home-page: https://docs.openstack.org/placement/latest/
Author: OpenStack
Author-email: openstack-discuss@lists.openstack.org
Project-URL: Bug Tracker, https://bugs.launchpad.net/placement
Project-URL: Documentation, https://docs.openstack.org/placement/latest/
Project-URL: API Reference, https://docs.openstack.org/api-ref/placement/
Project-URL: Source Code, https://opendev.org/openstack/placement
Project-URL: Release Notes, https://docs.openstack.org/releasenotes/placement/
Classifier: Development Status :: 5 - Production/Stable
Classifier: Environment :: OpenStack
Classifier: Intended Audience :: Information Technology
Classifier: Intended Audience :: System Administrators
Classifier: License :: OSI Approved :: Apache Software License
Classifier: Operating System :: POSIX :: Linux
Classifier: Programming Language :: Python
Classifier: Programming Language :: Python :: Implementation :: CPython
Classifier: Programming Language :: Python :: 3 :: Only
Classifier: Programming Language :: Python :: 3
Classifier: Programming Language :: Python :: 3.10
Classifier: Programming Language :: Python :: 3.11
Classifier: Programming Language :: Python :: 3.12
Requires-Python: >=3.10
License-File: LICENSE
License-File: AUTHORS
Requires-Dist: pbr >=3.1.1
Requires-Dist: SQLAlchemy >=1.4.0
Requires-Dist: keystonemiddleware >=4.18.0
Requires-Dist: Routes >=2.3.1
Requires-Dist: WebOb >=1.8.2
Requires-Dist: jsonschema >=3.2.0
Requires-Dist: requests >=2.25.0
Requires-Dist: oslo.concurrency >=3.26.0
Requires-Dist: oslo.config >=6.7.0
Requires-Dist: oslo.context >=2.22.0
Requires-Dist: oslo.log >=4.3.0
Requires-Dist: oslo.serialization >=2.25.0
Requires-Dist: oslo.utils >=4.5.0
Requires-Dist: oslo.db >=8.6.0
Requires-Dist: oslo.policy >=4.4.0
Requires-Dist: oslo.middleware >=3.31.0
Requires-Dist: oslo.upgradecheck >=1.3.0
Requires-Dist: os-resource-classes >=1.1.0
Requires-Dist: os-traits >=3.3.0
Requires-Dist: microversion-parse >=0.2.1
